quantum_spec_parser/__init__.py
quantum_spec_parser/main.py
quantum_spec_parser/prompts.py
quantum_spec_parser-2025.12.21131621.dist-info/METADATA
quantum_spec_parser-2025.12.21131621.dist-info/WHEEL
quantum_spec_parser-2025.12.21131621.dist-info/top_level.txt
quantum_spec_parser-2025.12.21131621.dist-info/RECORD
