Metadata-Version: 2.4
Name: quantum-spec-parser
Version: 2025.12.21131621
Summary: A new package designed to extract and structure key technical specifications from quantum computing research and development texts. The package takes unstructured text input describing quantum process
Author-email: quantum-spec-parser <hi@eugene.plus>
License: MIT
Project-URL: Homepage, https://github.com/chigwell/quantum-spec-parser
Requires-Python: >=3.9
Requires-Dist: langchain-llm7>=0.0.0
Requires-Dist: llmatch-messages>=0.0.0
Requires-Dist: langchain-core>=0.3.0
